xorlock
